almanet/__init__.py
almanet/_clients/__init__.py
almanet/_clients/_ansqd_tcp.py
almanet/_package.py
almanet/_service.py
almanet/_session.py
almanet/_shared/__init__.py
almanet/_shared/_background_tasks.py
almanet/_shared/_concurrent_context.py
almanet/_shared/_decoding.py
almanet/_shared/_encoding.py
almanet/_shared/_is_valid_uri.py
almanet/_shared/_new_id.py
almanet/_shared/_observable_event.py
almanet/_shared/_procedure.py
almanet/_shared/_streaming.py
almanet-1.3.4.dist-info/METADATA
almanet-1.3.4.dist-info/WHEEL
almanet-1.3.4.dist-info/licenses/LICENSE
almanet-1.3.4.dist-info/RECORD
