Metadata-Version: 2.4
Name: almanet
Version: 1.3.4
Summary: Web Messaging Protocol
License: MIT
License-File: LICENSE
Keywords: Almanet,PubSub,RPC
Author: aturkenov
Requires-Python: >=3.12,<4.0
Classifier: License :: OSI Approved :: MIT License
Classifier: Operating System :: OS Independent
Classifier: Programming Language :: Python
Classifier: Programming Language :: Python :: 3
Classifier: Programming Language :: Python :: 3.12
Classifier: Programming Language :: Python :: 3.13
Classifier: Programming Language :: Python :: 3.14
Classifier: Topic :: Software Development :: Libraries :: Python Modules
Classifier: Topic :: Software Development :: Object Brokering
Classifier: Topic :: System :: Distributed Computing
Requires-Dist: ansq (>=0.3.0,<0.4.0)
Requires-Dist: pydantic (>=2.7.1,<3.0.0)
Project-URL: Documentation, https://github.com/aturkenov/almanetpy
Project-URL: Homepage, https://github.com/aturkenov/almanetpy
Project-URL: Repository, https://github.com/aturkenov/almanetpy
